Metadata-Version: 1.1
Name: aiotimer
Version: 0.1.0
Summary: High resoltion timer for asyncio
Home-page: https://github.com/vodik/aiotimer
Author: Simon Gomizelj
Author-email: simon@vodik.xyz
License: Apache 2
Keywords: asyncio,timer,timerfd
Platform: UNKNOWN
Classifier: Development Status :: 2 - Pre-Alpha
Classifier: Intended Audience :: Developers
Classifier: License :: OSI Approved :: BSD License
Classifier: Natural Language :: English
Classifier: Programming Language :: Python :: 3
Classifier: Programming Language :: Python :: 3.4
Classifier: Programming Language :: Python :: 3.5
Classifier: Programming Language :: Python :: 3.6
